{
    "results": [
        {
            "title": "Scheduler Performance Comparison",
            "name": "TaskSubmission_V1",
            "unit": "operation",
            "batch": 1,
            "complexityN": -1,
            "epochs": 11,
            "clockResolution": 2e-08,
            "clockResolutionMultiple": 1000,
            "maxEpochTime": 0.1,
            "minEpochTime": 0.001,
            "minEpochIterations": 5,
            "epochIterations": 10,
            "warmup": 3,
            "relative": 1,
            "median(elapsed)": 0.0001453523,
            "medianAbsolutePercentError(elapsed)": 0.00889424076772481,
            "median(instructions)": 0,
            "medianAbsolutePercentError(instructions)": 0,
            "median(cpucycles)": 0,
            "median(contextswitches)": 0,
            "median(pagefaults)": 0,
            "median(branchinstructions)": 0,
            "median(branchmisses)": 0,
            "totalTime": 0.015550551,
            "measurements": [
                {
                    "iterations": 8,
                    "elapsed": 0.000138867875,
                    "pagefaults": 0,
                    "cpucycles": 0,
                    "contextswitches": 0,
                    "instructions": 0,
                    "branchinstructions": 0,
                    "branchmisses": 0
                },
                {
                    "iterations": 7,
                    "elapsed": 0.000143453428571429,
                    "pagefaults": 0,
                    "cpucycles": 0,
                    "contextswitches": 0,
                    "instructions": 0,
                    "branchinstructions": 0,
                    "branchmisses": 0
                },
                {
                    "iterations": 10,
                    "elapsed": 0.0001744005,
                    "pagefaults": 0,
                    "cpucycles": 0,
                    "contextswitches": 0,
                    "instructions": 0,
                    "branchinstructions": 0,
                    "branchmisses": 0
                },
                {
                    "iterations": 10,
                    "elapsed": 0.0001466567,
                    "pagefaults": 0,
                    "cpucycles": 0,
                    "contextswitches": 0,
                    "instructions": 0,
                    "branchinstructions": 0,
                    "branchmisses": 0
                },
                {
                    "iterations": 10,
                    "elapsed": 0.0001458502,
                    "pagefaults": 0,
                    "cpucycles": 0,
                    "contextswitches": 0,
                    "instructions": 0,
                    "branchinstructions": 0,
                    "branchmisses": 0
                },
                {
                    "iterations": 10,
                    "elapsed": 0.0001524625,
                    "pagefaults": 0,
                    "cpucycles": 0,
                    "contextswitches": 0,
                    "instructions": 0,
                    "branchinstructions": 0,
                    "branchmisses": 0
                },
                {
                    "iterations": 10,
                    "elapsed": 0.0001451739,
                    "pagefaults": 0,
                    "cpucycles": 0,
                    "contextswitches": 0,
                    "instructions": 0,
                    "branchinstructions": 0,
                    "branchmisses": 0
                },
                {
                    "iterations": 10,
                    "elapsed": 0.0001459484,
                    "pagefaults": 0,
                    "cpucycles": 0,
                    "contextswitches": 0,
                    "instructions": 0,
                    "branchinstructions": 0,
                    "branchmisses": 0
                },
                {
                    "iterations": 10,
                    "elapsed": 0.0001427424,
                    "pagefaults": 0,
                    "cpucycles": 0,
                    "contextswitches": 0,
                    "instructions": 0,
                    "branchinstructions": 0,
                    "branchmisses": 0
                },
                {
                    "iterations": 10,
                    "elapsed": 0.0001449565,
                    "pagefaults": 0,
                    "cpucycles": 0,
                    "contextswitches": 0,
                    "instructions": 0,
                    "branchinstructions": 0,
                    "branchmisses": 0
                },
                {
                    "iterations": 10,
                    "elapsed": 0.0001453523,
                    "pagefaults": 0,
                    "cpucycles": 0,
                    "contextswitches": 0,
                    "instructions": 0,
                    "branchinstructions": 0,
                    "branchmisses": 0
                }
            ]
        },
        {
            "title": "Scheduler Performance Comparison",
            "name": "TaskSubmission_V2",
            "unit": "operation",
            "batch": 1,
            "complexityN": -1,
            "epochs": 11,
            "clockResolution": 2e-08,
            "clockResolutionMultiple": 1000,
            "maxEpochTime": 0.1,
            "minEpochTime": 0.001,
            "minEpochIterations": 5,
            "epochIterations": 10,
            "warmup": 3,
            "relative": 1,
            "median(elapsed)": 0.0001273677,
            "medianAbsolutePercentError(elapsed)": 0.00347230100577813,
            "median(instructions)": 0,
            "medianAbsolutePercentError(instructions)": 0,
            "median(cpucycles)": 0,
            "median(contextswitches)": 0,
            "median(pagefaults)": 0,
            "median(branchinstructions)": 0,
            "median(branchmisses)": 0,
            "totalTime": 0.013354725,
            "measurements": [
                {
                    "iterations": 7,
                    "elapsed": 0.000126520571428571,
                    "pagefaults": 0,
                    "cpucycles": 0,
                    "contextswitches": 0,
                    "instructions": 0,
                    "branchinstructions": 0,
                    "branchmisses": 0
                },
                {
                    "iterations": 8,
                    "elapsed": 0.000127647,
                    "pagefaults": 0,
                    "cpucycles": 0,
                    "contextswitches": 0,
                    "instructions": 0,
                    "branchinstructions": 0,
                    "branchmisses": 0
                },
                {
                    "iterations": 10,
                    "elapsed": 0.0001273677,
                    "pagefaults": 0,
                    "cpucycles": 0,
                    "contextswitches": 0,
                    "instructions": 0,
                    "branchinstructions": 0,
                    "branchmisses": 0
                },
                {
                    "iterations": 10,
                    "elapsed": 0.0001254681,
                    "pagefaults": 0,
                    "cpucycles": 0,
                    "contextswitches": 0,
                    "instructions": 0,
                    "branchinstructions": 0,
                    "branchmisses": 0
                },
                {
                    "iterations": 10,
                    "elapsed": 0.0001272304,
                    "pagefaults": 0,
                    "cpucycles": 0,
                    "contextswitches": 0,
                    "instructions": 0,
                    "branchinstructions": 0,
                    "branchmisses": 0
                },
                {
                    "iterations": 10,
                    "elapsed": 0.0001278115,
                    "pagefaults": 0,
                    "cpucycles": 0,
                    "contextswitches": 0,
                    "instructions": 0,
                    "branchinstructions": 0,
                    "branchmisses": 0
                },
                {
                    "iterations": 10,
                    "elapsed": 0.0001275501,
                    "pagefaults": 0,
                    "cpucycles": 0,
                    "contextswitches": 0,
                    "instructions": 0,
                    "branchinstructions": 0,
                    "branchmisses": 0
                },
                {
                    "iterations": 10,
                    "elapsed": 0.0001270391,
                    "pagefaults": 0,
                    "cpucycles": 0,
                    "contextswitches": 0,
                    "instructions": 0,
                    "branchinstructions": 0,
                    "branchmisses": 0
                },
                {
                    "iterations": 10,
                    "elapsed": 0.0001263248,
                    "pagefaults": 0,
                    "cpucycles": 0,
                    "contextswitches": 0,
                    "instructions": 0,
                    "branchinstructions": 0,
                    "branchmisses": 0
                },
                {
                    "iterations": 10,
                    "elapsed": 0.0001279799,
                    "pagefaults": 0,
                    "cpucycles": 0,
                    "contextswitches": 0,
                    "instructions": 0,
                    "branchinstructions": 0,
                    "branchmisses": 0
                },
                {
                    "iterations": 10,
                    "elapsed": 0.0001280189,
                    "pagefaults": 0,
                    "cpucycles": 0,
                    "contextswitches": 0,
                    "instructions": 0,
                    "branchinstructions": 0,
                    "branchmisses": 0
                }
            ]
        },
        {
            "title": "Scheduler Performance Comparison",
            "name": "TaskSubmission_TBB",
            "unit": "operation",
            "batch": 1,
            "complexityN": -1,
            "epochs": 11,
            "clockResolution": 2e-08,
            "clockResolutionMultiple": 1000,
            "maxEpochTime": 0.1,
            "minEpochTime": 0.001,
            "minEpochIterations": 5,
            "epochIterations": 10,
            "warmup": 3,
            "relative": 1,
            "median(elapsed)": 0.0002469309,
            "medianAbsolutePercentError(elapsed)": 0.00743386835693974,
            "median(instructions)": 0,
            "medianAbsolutePercentError(instructions)": 0,
            "median(cpucycles)": 0,
            "median(contextswitches)": 0,
            "median(pagefaults)": 0,
            "median(branchinstructions)": 0,
            "median(branchmisses)": 0,
            "totalTime": 0.025995244,
            "measurements": [
                {
                    "iterations": 5,
                    "elapsed": 0.0002387434,
                    "pagefaults": 0,
                    "cpucycles": 0,
                    "contextswitches": 0,
                    "instructions": 0,
                    "branchinstructions": 0,
                    "branchmisses": 0
                },
                {
                    "iterations": 10,
                    "elapsed": 0.0002485499,
                    "pagefaults": 0,
                    "cpucycles": 0,
                    "contextswitches": 0,
                    "instructions": 0,
                    "branchinstructions": 0,
                    "branchmisses": 0
                },
                {
                    "iterations": 10,
                    "elapsed": 0.0002496108,
                    "pagefaults": 0,
                    "cpucycles": 0,
                    "contextswitches": 0,
                    "instructions": 0,
                    "branchinstructions": 0,
                    "branchmisses": 0
                },
                {
                    "iterations": 10,
                    "elapsed": 0.0002454661,
                    "pagefaults": 0,
                    "cpucycles": 0,
                    "contextswitches": 0,
                    "instructions": 0,
                    "branchinstructions": 0,
                    "branchmisses": 0
                },
                {
                    "iterations": 10,
                    "elapsed": 0.0002445274,
                    "pagefaults": 0,
                    "cpucycles": 0,
                    "contextswitches": 0,
                    "instructions": 0,
                    "branchinstructions": 0,
                    "branchmisses": 0
                },
                {
                    "iterations": 10,
                    "elapsed": 0.0002515885,
                    "pagefaults": 0,
                    "cpucycles": 0,
                    "contextswitches": 0,
                    "instructions": 0,
                    "branchinstructions": 0,
                    "branchmisses": 0
                },
                {
                    "iterations": 10,
                    "elapsed": 0.0002487803,
                    "pagefaults": 0,
                    "cpucycles": 0,
                    "contextswitches": 0,
                    "instructions": 0,
                    "branchinstructions": 0,
                    "branchmisses": 0
                },
                {
                    "iterations": 10,
                    "elapsed": 0.0002523139,
                    "pagefaults": 0,
                    "cpucycles": 0,
                    "contextswitches": 0,
                    "instructions": 0,
                    "branchinstructions": 0,
                    "branchmisses": 0
                },
                {
                    "iterations": 10,
                    "elapsed": 0.0002455062,
                    "pagefaults": 0,
                    "cpucycles": 0,
                    "contextswitches": 0,
                    "instructions": 0,
                    "branchinstructions": 0,
                    "branchmisses": 0
                },
                {
                    "iterations": 10,
                    "elapsed": 0.0002468787,
                    "pagefaults": 0,
                    "cpucycles": 0,
                    "contextswitches": 0,
                    "instructions": 0,
                    "branchinstructions": 0,
                    "branchmisses": 0
                },
                {
                    "iterations": 10,
                    "elapsed": 0.0002469309,
                    "pagefaults": 0,
                    "cpucycles": 0,
                    "contextswitches": 0,
                    "instructions": 0,
                    "branchinstructions": 0,
                    "branchmisses": 0
                }
            ]
        },
        {
            "title": "Scheduler Performance Comparison",
            "name": "ParallelFor_VectorOps_V1",
            "unit": "operation",
            "batch": 1,
            "complexityN": -1,
            "epochs": 11,
            "clockResolution": 2e-08,
            "clockResolutionMultiple": 1000,
            "maxEpochTime": 0.1,
            "minEpochTime": 0.001,
            "minEpochIterations": 5,
            "epochIterations": 10,
            "warmup": 3,
            "relative": 1,
            "median(elapsed)": 0.0002192062,
            "medianAbsolutePercentError(elapsed)": 0.00272264433171251,
            "median(instructions)": 0,
            "medianAbsolutePercentError(instructions)": 0,
            "median(cpucycles)": 0,
            "median(contextswitches)": 0,
            "median(pagefaults)": 0,
            "median(branchinstructions)": 0,
            "median(branchmisses)": 0,
            "totalTime": 0.023082477,
            "measurements": [
                {
                    "iterations": 5,
                    "elapsed": 0.0002274564,
                    "pagefaults": 0,
                    "cpucycles": 0,
                    "contextswitches": 0,
                    "instructions": 0,
                    "branchinstructions": 0,
                    "branchmisses": 0
                },
                {
                    "iterations": 10,
                    "elapsed": 0.0002198012,
                    "pagefaults": 0,
                    "cpucycles": 0,
                    "contextswitches": 0,
                    "instructions": 0,
                    "branchinstructions": 0,
                    "branchmisses": 0
                },
                {
                    "iterations": 10,
                    "elapsed": 0.0002190067,
                    "pagefaults": 0,
                    "cpucycles": 0,
                    "contextswitches": 0,
                    "instructions": 0,
                    "branchinstructions": 0,
                    "branchmisses": 0
                },
                {
                    "iterations": 10,
                    "elapsed": 0.000218611,
                    "pagefaults": 0,
                    "cpucycles": 0,
                    "contextswitches": 0,
                    "instructions": 0,
                    "branchinstructions": 0,
                    "branchmisses": 0
                },
                {
                    "iterations": 10,
                    "elapsed": 0.0002199755,
                    "pagefaults": 0,
                    "cpucycles": 0,
                    "contextswitches": 0,
                    "instructions": 0,
                    "branchinstructions": 0,
                    "branchmisses": 0
                },
                {
                    "iterations": 10,
                    "elapsed": 0.0002185929,
                    "pagefaults": 0,
                    "cpucycles": 0,
                    "contextswitches": 0,
                    "instructions": 0,
                    "branchinstructions": 0,
                    "branchmisses": 0
                },
                {
                    "iterations": 10,
                    "elapsed": 0.0002192062,
                    "pagefaults": 0,
                    "cpucycles": 0,
                    "contextswitches": 0,
                    "instructions": 0,
                    "branchinstructions": 0,
                    "branchmisses": 0
                },
                {
                    "iterations": 10,
                    "elapsed": 0.0002190929,
                    "pagefaults": 0,
                    "cpucycles": 0,
                    "contextswitches": 0,
                    "instructions": 0,
                    "branchinstructions": 0,
                    "branchmisses": 0
                },
                {
                    "iterations": 10,
                    "elapsed": 0.0002188374,
                    "pagefaults": 0,
                    "cpucycles": 0,
                    "contextswitches": 0,
                    "instructions": 0,
                    "branchinstructions": 0,
                    "branchmisses": 0
                },
                {
                    "iterations": 10,
                    "elapsed": 0.0002205215,
                    "pagefaults": 0,
                    "cpucycles": 0,
                    "contextswitches": 0,
                    "instructions": 0,
                    "branchinstructions": 0,
                    "branchmisses": 0
                },
                {
                    "iterations": 10,
                    "elapsed": 0.0002208742,
                    "pagefaults": 0,
                    "cpucycles": 0,
                    "contextswitches": 0,
                    "instructions": 0,
                    "branchinstructions": 0,
                    "branchmisses": 0
                }
            ]
        },
        {
            "title": "Scheduler Performance Comparison",
            "name": "ParallelFor_VectorOps_V2",
            "unit": "operation",
            "batch": 1,
            "complexityN": -1,
            "epochs": 11,
            "clockResolution": 2e-08,
            "clockResolutionMultiple": 1000,
            "maxEpochTime": 0.1,
            "minEpochTime": 0.001,
            "minEpochIterations": 5,
            "epochIterations": 10,
            "warmup": 3,
            "relative": 1,
            "median(elapsed)": 0.0002302628,
            "medianAbsolutePercentError(elapsed)": 0.0219204734879081,
            "median(instructions)": 0,
            "medianAbsolutePercentError(instructions)": 0,
            "median(cpucycles)": 0,
            "median(contextswitches)": 0,
            "median(pagefaults)": 0,
            "median(branchinstructions)": 0,
            "median(branchmisses)": 0,
            "totalTime": 0.024871448,
            "measurements": [
                {
                    "iterations": 5,
                    "elapsed": 0.0002266912,
                    "pagefaults": 0,
                    "cpucycles": 0,
                    "contextswitches": 0,
                    "instructions": 0,
                    "branchinstructions": 0,
                    "branchmisses": 0
                },
                {
                    "iterations": 10,
                    "elapsed": 0.0002413505,
                    "pagefaults": 0,
                    "cpucycles": 0,
                    "contextswitches": 0,
                    "instructions": 0,
                    "branchinstructions": 0,
                    "branchmisses": 0
                },
                {
                    "iterations": 10,
                    "elapsed": 0.0002401412,
                    "pagefaults": 0,
                    "cpucycles": 0,
                    "contextswitches": 0,
                    "instructions": 0,
                    "branchinstructions": 0,
                    "branchmisses": 0
                },
                {
                    "iterations": 10,
                    "elapsed": 0.0002681472,
                    "pagefaults": 0,
                    "cpucycles": 0,
                    "contextswitches": 0,
                    "instructions": 0,
                    "branchinstructions": 0,
                    "branchmisses": 0
                },
                {
                    "iterations": 10,
                    "elapsed": 0.0002281147,
                    "pagefaults": 0,
                    "cpucycles": 0,
                    "contextswitches": 0,
                    "instructions": 0,
                    "branchinstructions": 0,
                    "branchmisses": 0
                },
                {
                    "iterations": 10,
                    "elapsed": 0.0002253236,
                    "pagefaults": 0,
                    "cpucycles": 0,
                    "contextswitches": 0,
                    "instructions": 0,
                    "branchinstructions": 0,
                    "branchmisses": 0
                },
                {
                    "iterations": 10,
                    "elapsed": 0.000227705,
                    "pagefaults": 0,
                    "cpucycles": 0,
                    "contextswitches": 0,
                    "instructions": 0,
                    "branchinstructions": 0,
                    "branchmisses": 0
                },
                {
                    "iterations": 10,
                    "elapsed": 0.0002401582,
                    "pagefaults": 0,
                    "cpucycles": 0,
                    "contextswitches": 0,
                    "instructions": 0,
                    "branchinstructions": 0,
                    "branchmisses": 0
                },
                {
                    "iterations": 10,
                    "elapsed": 0.0002302628,
                    "pagefaults": 0,
                    "cpucycles": 0,
                    "contextswitches": 0,
                    "instructions": 0,
                    "branchinstructions": 0,
                    "branchmisses": 0
                },
                {
                    "iterations": 10,
                    "elapsed": 0.0002298459,
                    "pagefaults": 0,
                    "cpucycles": 0,
                    "contextswitches": 0,
                    "instructions": 0,
                    "branchinstructions": 0,
                    "branchmisses": 0
                },
                {
                    "iterations": 10,
                    "elapsed": 0.0002427501,
                    "pagefaults": 0,
                    "cpucycles": 0,
                    "contextswitches": 0,
                    "instructions": 0,
                    "branchinstructions": 0,
                    "branchmisses": 0
                }
            ]
        },
        {
            "title": "Scheduler Performance Comparison",
            "name": "ParallelFor_VectorOps_TBB",
            "unit": "operation",
            "batch": 1,
            "complexityN": -1,
            "epochs": 11,
            "clockResolution": 2e-08,
            "clockResolutionMultiple": 1000,
            "maxEpochTime": 0.1,
            "minEpochTime": 0.001,
            "minEpochIterations": 5,
            "epochIterations": 10,
            "warmup": 3,
            "relative": 1,
            "median(elapsed)": 0.0002366967,
            "medianAbsolutePercentError(elapsed)": 0.0467099153599194,
            "median(instructions)": 0,
            "medianAbsolutePercentError(instructions)": 0,
            "median(cpucycles)": 0,
            "median(contextswitches)": 0,
            "median(pagefaults)": 0,
            "median(branchinstructions)": 0,
            "median(branchmisses)": 0,
            "totalTime": 0.026100249,
            "measurements": [
                {
                    "iterations": 5,
                    "elapsed": 0.0002226674,
                    "pagefaults": 0,
                    "cpucycles": 0,
                    "contextswitches": 0,
                    "instructions": 0,
                    "branchinstructions": 0,
                    "branchmisses": 0
                },
                {
                    "iterations": 10,
                    "elapsed": 0.000222892,
                    "pagefaults": 0,
                    "cpucycles": 0,
                    "contextswitches": 0,
                    "instructions": 0,
                    "branchinstructions": 0,
                    "branchmisses": 0
                },
                {
                    "iterations": 10,
                    "elapsed": 0.0002472274,
                    "pagefaults": 0,
                    "cpucycles": 0,
                    "contextswitches": 0,
                    "instructions": 0,
                    "branchinstructions": 0,
                    "branchmisses": 0
                },
                {
                    "iterations": 10,
                    "elapsed": 0.0002336069,
                    "pagefaults": 0,
                    "cpucycles": 0,
                    "contextswitches": 0,
                    "instructions": 0,
                    "branchinstructions": 0,
                    "branchmisses": 0
                },
                {
                    "iterations": 10,
                    "elapsed": 0.0002246413,
                    "pagefaults": 0,
                    "cpucycles": 0,
                    "contextswitches": 0,
                    "instructions": 0,
                    "branchinstructions": 0,
                    "branchmisses": 0
                },
                {
                    "iterations": 10,
                    "elapsed": 0.0002366967,
                    "pagefaults": 0,
                    "cpucycles": 0,
                    "contextswitches": 0,
                    "instructions": 0,
                    "branchinstructions": 0,
                    "branchmisses": 0
                },
                {
                    "iterations": 10,
                    "elapsed": 0.000226134,
                    "pagefaults": 0,
                    "cpucycles": 0,
                    "contextswitches": 0,
                    "instructions": 0,
                    "branchinstructions": 0,
                    "branchmisses": 0
                },
                {
                    "iterations": 10,
                    "elapsed": 0.0003497127,
                    "pagefaults": 0,
                    "cpucycles": 0,
                    "contextswitches": 0,
                    "instructions": 0,
                    "branchinstructions": 0,
                    "branchmisses": 0
                },
                {
                    "iterations": 10,
                    "elapsed": 0.0002465952,
                    "pagefaults": 0,
                    "cpucycles": 0,
                    "contextswitches": 0,
                    "instructions": 0,
                    "branchinstructions": 0,
                    "branchmisses": 0
                },
                {
                    "iterations": 10,
                    "elapsed": 0.0002466874,
                    "pagefaults": 0,
                    "cpucycles": 0,
                    "contextswitches": 0,
                    "instructions": 0,
                    "branchinstructions": 0,
                    "branchmisses": 0
                },
                {
                    "iterations": 10,
                    "elapsed": 0.0002644976,
                    "pagefaults": 0,
                    "cpucycles": 0,
                    "contextswitches": 0,
                    "instructions": 0,
                    "branchinstructions": 0,
                    "branchmisses": 0
                }
            ]
        },
        {
            "title": "Scheduler Performance Comparison",
            "name": "MatrixOps_V1",
            "unit": "operation",
            "batch": 1,
            "complexityN": -1,
            "epochs": 11,
            "clockResolution": 2e-08,
            "clockResolutionMultiple": 1000,
            "maxEpochTime": 0.1,
            "minEpochTime": 0.001,
            "minEpochIterations": 5,
            "epochIterations": 10,
            "warmup": 3,
            "relative": 1,
            "median(elapsed)": 0.0001748313,
            "medianAbsolutePercentError(elapsed)": 0.03525084942876,
            "median(instructions)": 0,
            "medianAbsolutePercentError(instructions)": 0,
            "median(cpucycles)": 0,
            "median(contextswitches)": 0,
            "median(pagefaults)": 0,
            "median(branchinstructions)": 0,
            "median(branchmisses)": 0,
            "totalTime": 0.032103496,
            "measurements": [
                {
                    "iterations": 6,
                    "elapsed": 0.000170960666666667,
                    "pagefaults": 0,
                    "cpucycles": 0,
                    "contextswitches": 0,
                    "instructions": 0,
                    "branchinstructions": 0,
                    "branchmisses": 0
                },
                {
                    "iterations": 6,
                    "elapsed": 0.0001703145,
                    "pagefaults": 0,
                    "cpucycles": 0,
                    "contextswitches": 0,
                    "instructions": 0,
                    "branchinstructions": 0,
                    "branchmisses": 0
                },
                {
                    "iterations": 10,
                    "elapsed": 0.0004629019,
                    "pagefaults": 0,
                    "cpucycles": 0,
                    "contextswitches": 0,
                    "instructions": 0,
                    "branchinstructions": 0,
                    "branchmisses": 0
                },
                {
                    "iterations": 10,
                    "elapsed": 0.0001688782,
                    "pagefaults": 0,
                    "cpucycles": 0,
                    "contextswitches": 0,
                    "instructions": 0,
                    "branchinstructions": 0,
                    "branchmisses": 0
                },
                {
                    "iterations": 10,
                    "elapsed": 0.0004715631,
                    "pagefaults": 0,
                    "cpucycles": 0,
                    "contextswitches": 0,
                    "instructions": 0,
                    "branchinstructions": 0,
                    "branchmisses": 0
                },
                {
                    "iterations": 10,
                    "elapsed": 0.0004636694,
                    "pagefaults": 0,
                    "cpucycles": 0,
                    "contextswitches": 0,
                    "instructions": 0,
                    "branchinstructions": 0,
                    "branchmisses": 0
                },
                {
                    "iterations": 10,
                    "elapsed": 0.0001689753,
                    "pagefaults": 0,
                    "cpucycles": 0,
                    "contextswitches": 0,
                    "instructions": 0,
                    "branchinstructions": 0,
                    "branchmisses": 0
                },
                {
                    "iterations": 10,
                    "elapsed": 0.0004625062,
                    "pagefaults": 0,
                    "cpucycles": 0,
                    "contextswitches": 0,
                    "instructions": 0,
                    "branchinstructions": 0,
                    "branchmisses": 0
                },
                {
                    "iterations": 10,
                    "elapsed": 0.0001748313,
                    "pagefaults": 0,
                    "cpucycles": 0,
                    "contextswitches": 0,
                    "instructions": 0,
                    "branchinstructions": 0,
                    "branchmisses": 0
                },
                {
                    "iterations": 10,
                    "elapsed": 0.0004611186,
                    "pagefaults": 0,
                    "cpucycles": 0,
                    "contextswitches": 0,
                    "instructions": 0,
                    "branchinstructions": 0,
                    "branchmisses": 0
                },
                {
                    "iterations": 10,
                    "elapsed": 0.0001711405,
                    "pagefaults": 0,
                    "cpucycles": 0,
                    "contextswitches": 0,
                    "instructions": 0,
                    "branchinstructions": 0,
                    "branchmisses": 0
                }
            ]
        },
        {
            "title": "Scheduler Performance Comparison",
            "name": "MatrixOps_V2",
            "unit": "operation",
            "batch": 1,
            "complexityN": -1,
            "epochs": 11,
            "clockResolution": 2e-08,
            "clockResolutionMultiple": 1000,
            "maxEpochTime": 0.1,
            "minEpochTime": 0.001,
            "minEpochIterations": 5,
            "epochIterations": 10,
            "warmup": 3,
            "relative": 1,
            "median(elapsed)": 0.0001626185,
            "medianAbsolutePercentError(elapsed)": 0.0841963358866164,
            "median(instructions)": 0,
            "medianAbsolutePercentError(instructions)": 0,
            "median(cpucycles)": 0,
            "median(contextswitches)": 0,
            "median(pagefaults)": 0,
            "median(branchinstructions)": 0,
            "median(branchmisses)": 0,
            "totalTime": 0.016977621,
            "measurements": [
                {
                    "iterations": 6,
                    "elapsed": 0.000181007666666667,
                    "pagefaults": 0,
                    "cpucycles": 0,
                    "contextswitches": 0,
                    "instructions": 0,
                    "branchinstructions": 0,
                    "branchmisses": 0
                },
                {
                    "iterations": 6,
                    "elapsed": 0.000180944333333333,
                    "pagefaults": 0,
                    "cpucycles": 0,
                    "contextswitches": 0,
                    "instructions": 0,
                    "branchinstructions": 0,
                    "branchmisses": 0
                },
                {
                    "iterations": 10,
                    "elapsed": 0.0001818834,
                    "pagefaults": 0,
                    "cpucycles": 0,
                    "contextswitches": 0,
                    "instructions": 0,
                    "branchinstructions": 0,
                    "branchmisses": 0
                },
                {
                    "iterations": 10,
                    "elapsed": 0.0001499899,
                    "pagefaults": 0,
                    "cpucycles": 0,
                    "contextswitches": 0,
                    "instructions": 0,
                    "branchinstructions": 0,
                    "branchmisses": 0
                },
                {
                    "iterations": 10,
                    "elapsed": 0.0001573356,
                    "pagefaults": 0,
                    "cpucycles": 0,
                    "contextswitches": 0,
                    "instructions": 0,
                    "branchinstructions": 0,
                    "branchmisses": 0
                },
                {
                    "iterations": 10,
                    "elapsed": 0.0001437873,
                    "pagefaults": 0,
                    "cpucycles": 0,
                    "contextswitches": 0,
                    "instructions": 0,
                    "branchinstructions": 0,
                    "branchmisses": 0
                },
                {
                    "iterations": 10,
                    "elapsed": 0.0001957703,
                    "pagefaults": 0,
                    "cpucycles": 0,
                    "contextswitches": 0,
                    "instructions": 0,
                    "branchinstructions": 0,
                    "branchmisses": 0
                },
                {
                    "iterations": 10,
                    "elapsed": 0.0001626185,
                    "pagefaults": 0,
                    "cpucycles": 0,
                    "contextswitches": 0,
                    "instructions": 0,
                    "branchinstructions": 0,
                    "branchmisses": 0
                },
                {
                    "iterations": 10,
                    "elapsed": 0.0001652905,
                    "pagefaults": 0,
                    "cpucycles": 0,
                    "contextswitches": 0,
                    "instructions": 0,
                    "branchinstructions": 0,
                    "branchmisses": 0
                },
                {
                    "iterations": 10,
                    "elapsed": 0.0001624982,
                    "pagefaults": 0,
                    "cpucycles": 0,
                    "contextswitches": 0,
                    "instructions": 0,
                    "branchinstructions": 0,
                    "branchmisses": 0
                },
                {
                    "iterations": 10,
                    "elapsed": 0.0001614172,
                    "pagefaults": 0,
                    "cpucycles": 0,
                    "contextswitches": 0,
                    "instructions": 0,
                    "branchinstructions": 0,
                    "branchmisses": 0
                }
            ]
        },
        {
            "title": "Scheduler Performance Comparison",
            "name": "MatrixOps_TBB",
            "unit": "operation",
            "batch": 1,
            "complexityN": -1,
            "epochs": 11,
            "clockResolution": 2e-08,
            "clockResolutionMultiple": 1000,
            "maxEpochTime": 0.1,
            "minEpochTime": 0.001,
            "minEpochIterations": 5,
            "epochIterations": 10,
            "warmup": 3,
            "relative": 1,
            "median(elapsed)": 0.0001614744,
            "medianAbsolutePercentError(elapsed)": 0.272573286908793,
            "median(instructions)": 0,
            "medianAbsolutePercentError(instructions)": 0,
            "median(cpucycles)": 0,
            "median(contextswitches)": 0,
            "median(pagefaults)": 0,
            "median(branchinstructions)": 0,
            "median(branchmisses)": 0,
            "totalTime": 0.018158111,
            "measurements": [
                {
                    "iterations": 7,
                    "elapsed": 0.000115094714285714,
                    "pagefaults": 0,
                    "cpucycles": 0,
                    "contextswitches": 0,
                    "instructions": 0,
                    "branchinstructions": 0,
                    "branchmisses": 0
                },
                {
                    "iterations": 9,
                    "elapsed": 0.000113865888888889,
                    "pagefaults": 0,
                    "cpucycles": 0,
                    "contextswitches": 0,
                    "instructions": 0,
                    "branchinstructions": 0,
                    "branchmisses": 0
                },
                {
                    "iterations": 10,
                    "elapsed": 0.0002119165,
                    "pagefaults": 0,
                    "cpucycles": 0,
                    "contextswitches": 0,
                    "instructions": 0,
                    "branchinstructions": 0,
                    "branchmisses": 0
                },
                {
                    "iterations": 10,
                    "elapsed": 0.0001533312,
                    "pagefaults": 0,
                    "cpucycles": 0,
                    "contextswitches": 0,
                    "instructions": 0,
                    "branchinstructions": 0,
                    "branchmisses": 0
                },
                {
                    "iterations": 10,
                    "elapsed": 0.0002184758,
                    "pagefaults": 0,
                    "cpucycles": 0,
                    "contextswitches": 0,
                    "instructions": 0,
                    "branchinstructions": 0,
                    "branchmisses": 0
                },
                {
                    "iterations": 10,
                    "elapsed": 0.0001614744,
                    "pagefaults": 0,
                    "cpucycles": 0,
                    "contextswitches": 0,
                    "instructions": 0,
                    "branchinstructions": 0,
                    "branchmisses": 0
                },
                {
                    "iterations": 10,
                    "elapsed": 0.0001133516,
                    "pagefaults": 0,
                    "cpucycles": 0,
                    "contextswitches": 0,
                    "instructions": 0,
                    "branchinstructions": 0,
                    "branchmisses": 0
                },
                {
                    "iterations": 10,
                    "elapsed": 0.0001157581,
                    "pagefaults": 0,
                    "cpucycles": 0,
                    "contextswitches": 0,
                    "instructions": 0,
                    "branchinstructions": 0,
                    "branchmisses": 0
                },
                {
                    "iterations": 10,
                    "elapsed": 0.0001891911,
                    "pagefaults": 0,
                    "cpucycles": 0,
                    "contextswitches": 0,
                    "instructions": 0,
                    "branchinstructions": 0,
                    "branchmisses": 0
                },
                {
                    "iterations": 10,
                    "elapsed": 0.0002219803,
                    "pagefaults": 0,
                    "cpucycles": 0,
                    "contextswitches": 0,
                    "instructions": 0,
                    "branchinstructions": 0,
                    "branchmisses": 0
                },
                {
                    "iterations": 10,
                    "elapsed": 0.0002472865,
                    "pagefaults": 0,
                    "cpucycles": 0,
                    "contextswitches": 0,
                    "instructions": 0,
                    "branchinstructions": 0,
                    "branchmisses": 0
                }
            ]
        },
        {
            "title": "Scheduler Performance Comparison",
            "name": "MixedWorkload_V1",
            "unit": "operation",
            "batch": 1,
            "complexityN": -1,
            "epochs": 11,
            "clockResolution": 2e-08,
            "clockResolutionMultiple": 1000,
            "maxEpochTime": 0.1,
            "minEpochTime": 0.001,
            "minEpochIterations": 5,
            "epochIterations": 10,
            "warmup": 3,
            "relative": 1,
            "median(elapsed)": 0.0003921328,
            "medianAbsolutePercentError(elapsed)": 0.157093749301398,
            "median(instructions)": 0,
            "medianAbsolutePercentError(instructions)": 0,
            "median(cpucycles)": 0,
            "median(contextswitches)": 0,
            "median(pagefaults)": 0,
            "median(branchinstructions)": 0,
            "median(branchmisses)": 0,
            "totalTime": 0.040838582,
            "measurements": [
                {
                    "iterations": 5,
                    "elapsed": 0.0005007966,
                    "pagefaults": 0,
                    "cpucycles": 0,
                    "contextswitches": 0,
                    "instructions": 0,
                    "branchinstructions": 0,
                    "branchmisses": 0
                },
                {
                    "iterations": 10,
                    "elapsed": 0.0003940339,
                    "pagefaults": 0,
                    "cpucycles": 0,
                    "contextswitches": 0,
                    "instructions": 0,
                    "branchinstructions": 0,
                    "branchmisses": 0
                },
                {
                    "iterations": 10,
                    "elapsed": 0.0004659947,
                    "pagefaults": 0,
                    "cpucycles": 0,
                    "contextswitches": 0,
                    "instructions": 0,
                    "branchinstructions": 0,
                    "branchmisses": 0
                },
                {
                    "iterations": 10,
                    "elapsed": 0.0003381291,
                    "pagefaults": 0,
                    "cpucycles": 0,
                    "contextswitches": 0,
                    "instructions": 0,
                    "branchinstructions": 0,
                    "branchmisses": 0
                },
                {
                    "iterations": 10,
                    "elapsed": 0.0003666783,
                    "pagefaults": 0,
                    "cpucycles": 0,
                    "contextswitches": 0,
                    "instructions": 0,
                    "branchinstructions": 0,
                    "branchmisses": 0
                },
                {
                    "iterations": 10,
                    "elapsed": 0.0003994415,
                    "pagefaults": 0,
                    "cpucycles": 0,
                    "contextswitches": 0,
                    "instructions": 0,
                    "branchinstructions": 0,
                    "branchmisses": 0
                },
                {
                    "iterations": 10,
                    "elapsed": 0.0004652152,
                    "pagefaults": 0,
                    "cpucycles": 0,
                    "contextswitches": 0,
                    "instructions": 0,
                    "branchinstructions": 0,
                    "branchmisses": 0
                },
                {
                    "iterations": 10,
                    "elapsed": 0.0003264562,
                    "pagefaults": 0,
                    "cpucycles": 0,
                    "contextswitches": 0,
                    "instructions": 0,
                    "branchinstructions": 0,
                    "branchmisses": 0
                },
                {
                    "iterations": 10,
                    "elapsed": 0.0003687513,
                    "pagefaults": 0,
                    "cpucycles": 0,
                    "contextswitches": 0,
                    "instructions": 0,
                    "branchinstructions": 0,
                    "branchmisses": 0
                },
                {
                    "iterations": 10,
                    "elapsed": 0.0003921328,
                    "pagefaults": 0,
                    "cpucycles": 0,
                    "contextswitches": 0,
                    "instructions": 0,
                    "branchinstructions": 0,
                    "branchmisses": 0
                },
                {
                    "iterations": 10,
                    "elapsed": 0.0003166269,
                    "pagefaults": 0,
                    "cpucycles": 0,
                    "contextswitches": 0,
                    "instructions": 0,
                    "branchinstructions": 0,
                    "branchmisses": 0
                }
            ]
        },
        {
            "title": "Scheduler Performance Comparison",
            "name": "MixedWorkload_V2",
            "unit": "operation",
            "batch": 1,
            "complexityN": -1,
            "epochs": 11,
            "clockResolution": 2e-08,
            "clockResolutionMultiple": 1000,
            "maxEpochTime": 0.1,
            "minEpochTime": 0.001,
            "minEpochIterations": 5,
            "epochIterations": 10,
            "warmup": 3,
            "relative": 1,
            "median(elapsed)": 0.0004455756,
            "medianAbsolutePercentError(elapsed)": 0.0549304124492395,
            "median(instructions)": 0,
            "medianAbsolutePercentError(instructions)": 0,
            "median(cpucycles)": 0,
            "median(contextswitches)": 0,
            "median(pagefaults)": 0,
            "median(branchinstructions)": 0,
            "median(branchmisses)": 0,
            "totalTime": 0.047154793,
            "measurements": [
                {
                    "iterations": 5,
                    "elapsed": 0.0004223744,
                    "pagefaults": 0,
                    "cpucycles": 0,
                    "contextswitches": 0,
                    "instructions": 0,
                    "branchinstructions": 0,
                    "branchmisses": 0
                },
                {
                    "iterations": 10,
                    "elapsed": 0.0004876001,
                    "pagefaults": 0,
                    "cpucycles": 0,
                    "contextswitches": 0,
                    "instructions": 0,
                    "branchinstructions": 0,
                    "branchmisses": 0
                },
                {
                    "iterations": 10,
                    "elapsed": 0.0005183684,
                    "pagefaults": 0,
                    "cpucycles": 0,
                    "contextswitches": 0,
                    "instructions": 0,
                    "branchinstructions": 0,
                    "branchmisses": 0
                },
                {
                    "iterations": 10,
                    "elapsed": 0.000447552,
                    "pagefaults": 0,
                    "cpucycles": 0,
                    "contextswitches": 0,
                    "instructions": 0,
                    "branchinstructions": 0,
                    "branchmisses": 0
                },
                {
                    "iterations": 10,
                    "elapsed": 0.0004017908,
                    "pagefaults": 0,
                    "cpucycles": 0,
                    "contextswitches": 0,
                    "instructions": 0,
                    "branchinstructions": 0,
                    "branchmisses": 0
                },
                {
                    "iterations": 10,
                    "elapsed": 0.0003977453,
                    "pagefaults": 0,
                    "cpucycles": 0,
                    "contextswitches": 0,
                    "instructions": 0,
                    "branchinstructions": 0,
                    "branchmisses": 0
                },
                {
                    "iterations": 10,
                    "elapsed": 0.0004434997,
                    "pagefaults": 0,
                    "cpucycles": 0,
                    "contextswitches": 0,
                    "instructions": 0,
                    "branchinstructions": 0,
                    "branchmisses": 0
                },
                {
                    "iterations": 10,
                    "elapsed": 0.0004376528,
                    "pagefaults": 0,
                    "cpucycles": 0,
                    "contextswitches": 0,
                    "instructions": 0,
                    "branchinstructions": 0,
                    "branchmisses": 0
                },
                {
                    "iterations": 10,
                    "elapsed": 0.0004749384,
                    "pagefaults": 0,
                    "cpucycles": 0,
                    "contextswitches": 0,
                    "instructions": 0,
                    "branchinstructions": 0,
                    "branchmisses": 0
                },
                {
                    "iterations": 10,
                    "elapsed": 0.000449569,
                    "pagefaults": 0,
                    "cpucycles": 0,
                    "contextswitches": 0,
                    "instructions": 0,
                    "branchinstructions": 0,
                    "branchmisses": 0
                },
                {
                    "iterations": 10,
                    "elapsed": 0.0004455756,
                    "pagefaults": 0,
                    "cpucycles": 0,
                    "contextswitches": 0,
                    "instructions": 0,
                    "branchinstructions": 0,
                    "branchmisses": 0
                }
            ]
        },
        {
            "title": "Scheduler Performance Comparison",
            "name": "MixedWorkload_TBB",
            "unit": "operation",
            "batch": 1,
            "complexityN": -1,
            "epochs": 11,
            "clockResolution": 2e-08,
            "clockResolutionMultiple": 1000,
            "maxEpochTime": 0.1,
            "minEpochTime": 0.001,
            "minEpochIterations": 5,
            "epochIterations": 10,
            "warmup": 3,
            "relative": 1,
            "median(elapsed)": 0.0004662792,
            "medianAbsolutePercentError(elapsed)": 0.0399503263845584,
            "median(instructions)": 0,
            "medianAbsolutePercentError(instructions)": 0,
            "median(cpucycles)": 0,
            "median(contextswitches)": 0,
            "median(pagefaults)": 0,
            "median(branchinstructions)": 0,
            "median(branchmisses)": 0,
            "totalTime": 0.051067274,
            "measurements": [
                {
                    "iterations": 5,
                    "elapsed": 0.0007330334,
                    "pagefaults": 0,
                    "cpucycles": 0,
                    "contextswitches": 0,
                    "instructions": 0,
                    "branchinstructions": 0,
                    "branchmisses": 0
                },
                {
                    "iterations": 10,
                    "elapsed": 0.0006980227,
                    "pagefaults": 0,
                    "cpucycles": 0,
                    "contextswitches": 0,
                    "instructions": 0,
                    "branchinstructions": 0,
                    "branchmisses": 0
                },
                {
                    "iterations": 10,
                    "elapsed": 0.0004662792,
                    "pagefaults": 0,
                    "cpucycles": 0,
                    "contextswitches": 0,
                    "instructions": 0,
                    "branchinstructions": 0,
                    "branchmisses": 0
                },
                {
                    "iterations": 10,
                    "elapsed": 0.000464031,
                    "pagefaults": 0,
                    "cpucycles": 0,
                    "contextswitches": 0,
                    "instructions": 0,
                    "branchinstructions": 0,
                    "branchmisses": 0
                },
                {
                    "iterations": 10,
                    "elapsed": 0.0004665477,
                    "pagefaults": 0,
                    "cpucycles": 0,
                    "contextswitches": 0,
                    "instructions": 0,
                    "branchinstructions": 0,
                    "branchmisses": 0
                },
                {
                    "iterations": 10,
                    "elapsed": 0.000466671,
                    "pagefaults": 0,
                    "cpucycles": 0,
                    "contextswitches": 0,
                    "instructions": 0,
                    "branchinstructions": 0,
                    "branchmisses": 0
                },
                {
                    "iterations": 10,
                    "elapsed": 0.0004635121,
                    "pagefaults": 0,
                    "cpucycles": 0,
                    "contextswitches": 0,
                    "instructions": 0,
                    "branchinstructions": 0,
                    "branchmisses": 0
                },
                {
                    "iterations": 10,
                    "elapsed": 0.0005301804,
                    "pagefaults": 0,
                    "cpucycles": 0,
                    "contextswitches": 0,
                    "instructions": 0,
                    "branchinstructions": 0,
                    "branchmisses": 0
                },
                {
                    "iterations": 10,
                    "elapsed": 0.0004483668,
                    "pagefaults": 0,
                    "cpucycles": 0,
                    "contextswitches": 0,
                    "instructions": 0,
                    "branchinstructions": 0,
                    "branchmisses": 0
                },
                {
                    "iterations": 10,
                    "elapsed": 0.00037449,
                    "pagefaults": 0,
                    "cpucycles": 0,
                    "contextswitches": 0,
                    "instructions": 0,
                    "branchinstructions": 0,
                    "branchmisses": 0
                },
                {
                    "iterations": 10,
                    "elapsed": 0.0003621098,
                    "pagefaults": 0,
                    "cpucycles": 0,
                    "contextswitches": 0,
                    "instructions": 0,
                    "branchinstructions": 0,
                    "branchmisses": 0
                }
            ]
        },
        {
            "title": "Scheduler Performance Comparison",
            "name": "TaskThroughput_V1",
            "unit": "operation",
            "batch": 1,
            "complexityN": -1,
            "epochs": 11,
            "clockResolution": 2e-08,
            "clockResolutionMultiple": 1000,
            "maxEpochTime": 0.1,
            "minEpochTime": 0.001,
            "minEpochIterations": 5,
            "epochIterations": 10,
            "warmup": 3,
            "relative": 1,
            "median(elapsed)": 0.0510337819,
            "medianAbsolutePercentError(elapsed)": 0.00211228751710541,
            "median(instructions)": 0,
            "medianAbsolutePercentError(instructions)": 0,
            "median(cpucycles)": 0,
            "median(contextswitches)": 0,
            "median(pagefaults)": 0,
            "median(branchinstructions)": 0,
            "median(branchmisses)": 0,
            "totalTime": 5.496075882,
            "measurements": [
                {
                    "iterations": 5,
                    "elapsed": 0.055436186,
                    "pagefaults": 0,
                    "cpucycles": 0,
                    "contextswitches": 0,
                    "instructions": 0,
                    "branchinstructions": 0,
                    "branchmisses": 0
                },
                {
                    "iterations": 10,
                    "elapsed": 0.062166049,
                    "pagefaults": 0,
                    "cpucycles": 0,
                    "contextswitches": 0,
                    "instructions": 0,
                    "branchinstructions": 0,
                    "branchmisses": 0
                },
                {
                    "iterations": 10,
                    "elapsed": 0.0509407453,
                    "pagefaults": 0,
                    "cpucycles": 0,
                    "contextswitches": 0,
                    "instructions": 0,
                    "branchinstructions": 0,
                    "branchmisses": 0
                },
                {
                    "iterations": 10,
                    "elapsed": 0.0509301264,
                    "pagefaults": 0,
                    "cpucycles": 0,
                    "contextswitches": 0,
                    "instructions": 0,
                    "branchinstructions": 0,
                    "branchmisses": 0
                },
                {
                    "iterations": 10,
                    "elapsed": 0.0518943149,
                    "pagefaults": 0,
                    "cpucycles": 0,
                    "contextswitches": 0,
                    "instructions": 0,
                    "branchinstructions": 0,
                    "branchmisses": 0
                },
                {
                    "iterations": 10,
                    "elapsed": 0.0509193814,
                    "pagefaults": 0,
                    "cpucycles": 0,
                    "contextswitches": 0,
                    "instructions": 0,
                    "branchinstructions": 0,
                    "branchmisses": 0
                },
                {
                    "iterations": 10,
                    "elapsed": 0.0510337819,
                    "pagefaults": 0,
                    "cpucycles": 0,
                    "contextswitches": 0,
                    "instructions": 0,
                    "branchinstructions": 0,
                    "branchmisses": 0
                },
                {
                    "iterations": 10,
                    "elapsed": 0.0509262111,
                    "pagefaults": 0,
                    "cpucycles": 0,
                    "contextswitches": 0,
                    "instructions": 0,
                    "branchinstructions": 0,
                    "branchmisses": 0
                },
                {
                    "iterations": 10,
                    "elapsed": 0.0511376624,
                    "pagefaults": 0,
                    "cpucycles": 0,
                    "contextswitches": 0,
                    "instructions": 0,
                    "branchinstructions": 0,
                    "branchmisses": 0
                },
                {
                    "iterations": 10,
                    "elapsed": 0.0508933318,
                    "pagefaults": 0,
                    "cpucycles": 0,
                    "contextswitches": 0,
                    "instructions": 0,
                    "branchinstructions": 0,
                    "branchmisses": 0
                },
                {
                    "iterations": 10,
                    "elapsed": 0.051047891,
                    "pagefaults": 0,
                    "cpucycles": 0,
                    "contextswitches": 0,
                    "instructions": 0,
                    "branchinstructions": 0,
                    "branchmisses": 0
                }
            ]
        },
        {
            "title": "Scheduler Performance Comparison",
            "name": "TaskThroughput_V2",
            "unit": "operation",
            "batch": 1,
            "complexityN": -1,
            "epochs": 11,
            "clockResolution": 2e-08,
            "clockResolutionMultiple": 1000,
            "maxEpochTime": 0.1,
            "minEpochTime": 0.001,
            "minEpochIterations": 5,
            "epochIterations": 10,
            "warmup": 3,
            "relative": 1,
            "median(elapsed)": 0.0607755038,
            "medianAbsolutePercentError(elapsed)": 0.00432331036893379,
            "median(instructions)": 0,
            "medianAbsolutePercentError(instructions)": 0,
            "median(cpucycles)": 0,
            "median(contextswitches)": 0,
            "median(pagefaults)": 0,
            "median(branchinstructions)": 0,
            "median(branchmisses)": 0,
            "totalTime": 6.62381013,
            "measurements": [
                {
                    "iterations": 5,
                    "elapsed": 0.07006993,
                    "pagefaults": 0,
                    "cpucycles": 0,
                    "contextswitches": 0,
                    "instructions": 0,
                    "branchinstructions": 0,
                    "branchmisses": 0
                },
                {
                    "iterations": 10,
                    "elapsed": 0.0605735553,
                    "pagefaults": 0,
                    "cpucycles": 0,
                    "contextswitches": 0,
                    "instructions": 0,
                    "branchinstructions": 0,
                    "branchmisses": 0
                },
                {
                    "iterations": 10,
                    "elapsed": 0.0608172447,
                    "pagefaults": 0,
                    "cpucycles": 0,
                    "contextswitches": 0,
                    "instructions": 0,
                    "branchinstructions": 0,
                    "branchmisses": 0
                },
                {
                    "iterations": 10,
                    "elapsed": 0.0676270328,
                    "pagefaults": 0,
                    "cpucycles": 0,
                    "contextswitches": 0,
                    "instructions": 0,
                    "branchinstructions": 0,
                    "branchmisses": 0
                },
                {
                    "iterations": 10,
                    "elapsed": 0.0607755038,
                    "pagefaults": 0,
                    "cpucycles": 0,
                    "contextswitches": 0,
                    "instructions": 0,
                    "branchinstructions": 0,
                    "branchmisses": 0
                },
                {
                    "iterations": 10,
                    "elapsed": 0.0557036338,
                    "pagefaults": 0,
                    "cpucycles": 0,
                    "contextswitches": 0,
                    "instructions": 0,
                    "branchinstructions": 0,
                    "branchmisses": 0
                },
                {
                    "iterations": 10,
                    "elapsed": 0.0605331695,
                    "pagefaults": 0,
                    "cpucycles": 0,
                    "contextswitches": 0,
                    "instructions": 0,
                    "branchinstructions": 0,
                    "branchmisses": 0
                },
                {
                    "iterations": 10,
                    "elapsed": 0.0605138835,
                    "pagefaults": 0,
                    "cpucycles": 0,
                    "contextswitches": 0,
                    "instructions": 0,
                    "branchinstructions": 0,
                    "branchmisses": 0
                },
                {
                    "iterations": 10,
                    "elapsed": 0.0702534321,
                    "pagefaults": 0,
                    "cpucycles": 0,
                    "contextswitches": 0,
                    "instructions": 0,
                    "branchinstructions": 0,
                    "branchmisses": 0
                },
                {
                    "iterations": 10,
                    "elapsed": 0.060551618,
                    "pagefaults": 0,
                    "cpucycles": 0,
                    "contextswitches": 0,
                    "instructions": 0,
                    "branchinstructions": 0,
                    "branchmisses": 0
                },
                {
                    "iterations": 10,
                    "elapsed": 0.0699969745,
                    "pagefaults": 0,
                    "cpucycles": 0,
                    "contextswitches": 0,
                    "instructions": 0,
                    "branchinstructions": 0,
                    "branchmisses": 0
                }
            ]
        },
        {
            "title": "Scheduler Performance Comparison",
            "name": "TaskThroughput_TBB",
            "unit": "operation",
            "batch": 1,
            "complexityN": -1,
            "epochs": 11,
            "clockResolution": 2e-08,
            "clockResolutionMultiple": 1000,
            "maxEpochTime": 0.1,
            "minEpochTime": 0.001,
            "minEpochIterations": 5,
            "epochIterations": 10,
            "warmup": 3,
            "relative": 1,
            "median(elapsed)": 0.0510215268,
            "medianAbsolutePercentError(elapsed)": 0.000543275603119201,
            "median(instructions)": 0,
            "medianAbsolutePercentError(instructions)": 0,
            "median(cpucycles)": 0,
            "median(contextswitches)": 0,
            "median(pagefaults)": 0,
            "median(branchinstructions)": 0,
            "median(branchmisses)": 0,
            "totalTime": 5.361227666,
            "measurements": [
                {
                    "iterations": 5,
                    "elapsed": 0.051004444,
                    "pagefaults": 0,
                    "cpucycles": 0,
                    "contextswitches": 0,
                    "instructions": 0,
                    "branchinstructions": 0,
                    "branchmisses": 0
                },
                {
                    "iterations": 10,
                    "elapsed": 0.0509886675,
                    "pagefaults": 0,
                    "cpucycles": 0,
                    "contextswitches": 0,
                    "instructions": 0,
                    "branchinstructions": 0,
                    "branchmisses": 0
                },
                {
                    "iterations": 10,
                    "elapsed": 0.0510565632,
                    "pagefaults": 0,
                    "cpucycles": 0,
                    "contextswitches": 0,
                    "instructions": 0,
                    "branchinstructions": 0,
                    "branchmisses": 0
                },
                {
                    "iterations": 10,
                    "elapsed": 0.0509938231,
                    "pagefaults": 0,
                    "cpucycles": 0,
                    "contextswitches": 0,
                    "instructions": 0,
                    "branchinstructions": 0,
                    "branchmisses": 0
                },
                {
                    "iterations": 10,
                    "elapsed": 0.0510892723,
                    "pagefaults": 0,
                    "cpucycles": 0,
                    "contextswitches": 0,
                    "instructions": 0,
                    "branchinstructions": 0,
                    "branchmisses": 0
                },
                {
                    "iterations": 10,
                    "elapsed": 0.0510215268,
                    "pagefaults": 0,
                    "cpucycles": 0,
                    "contextswitches": 0,
                    "instructions": 0,
                    "branchinstructions": 0,
                    "branchmisses": 0
                },
                {
                    "iterations": 10,
                    "elapsed": 0.0510211942,
                    "pagefaults": 0,
                    "cpucycles": 0,
                    "contextswitches": 0,
                    "instructions": 0,
                    "branchinstructions": 0,
                    "branchmisses": 0
                },
                {
                    "iterations": 10,
                    "elapsed": 0.0510734988,
                    "pagefaults": 0,
                    "cpucycles": 0,
                    "contextswitches": 0,
                    "instructions": 0,
                    "branchinstructions": 0,
                    "branchmisses": 0
                },
                {
                    "iterations": 10,
                    "elapsed": 0.0510463912,
                    "pagefaults": 0,
                    "cpucycles": 0,
                    "contextswitches": 0,
                    "instructions": 0,
                    "branchinstructions": 0,
                    "branchmisses": 0
                },
                {
                    "iterations": 10,
                    "elapsed": 0.0509999225,
                    "pagefaults": 0,
                    "cpucycles": 0,
                    "contextswitches": 0,
                    "instructions": 0,
                    "branchinstructions": 0,
                    "branchmisses": 0
                },
                {
                    "iterations": 10,
                    "elapsed": 0.051329685,
                    "pagefaults": 0,
                    "cpucycles": 0,
                    "contextswitches": 0,
                    "instructions": 0,
                    "branchinstructions": 0,
                    "branchmisses": 0
                }
            ]
        },
        {
            "title": "Scheduler Performance Comparison",
            "name": "NestedParallel_V1",
            "unit": "operation",
            "batch": 1,
            "complexityN": -1,
            "epochs": 11,
            "clockResolution": 2e-08,
            "clockResolutionMultiple": 1000,
            "maxEpochTime": 0.1,
            "minEpochTime": 0.001,
            "minEpochIterations": 5,
            "epochIterations": 10,
            "warmup": 3,
            "relative": 1,
            "median(elapsed)": 0.0001163081,
            "medianAbsolutePercentError(elapsed)": 0.00376103693462551,
            "median(instructions)": 0,
            "medianAbsolutePercentError(instructions)": 0,
            "median(cpucycles)": 0,
            "median(contextswitches)": 0,
            "median(pagefaults)": 0,
            "median(branchinstructions)": 0,
            "median(branchmisses)": 0,
            "totalTime": 0.016001528,
            "measurements": [
                {
                    "iterations": 5,
                    "elapsed": 0.0002316964,
                    "pagefaults": 0,
                    "cpucycles": 0,
                    "contextswitches": 0,
                    "instructions": 0,
                    "branchinstructions": 0,
                    "branchmisses": 0
                },
                {
                    "iterations": 10,
                    "elapsed": 0.0002367418,
                    "pagefaults": 0,
                    "cpucycles": 0,
                    "contextswitches": 0,
                    "instructions": 0,
                    "branchinstructions": 0,
                    "branchmisses": 0
                },
                {
                    "iterations": 10,
                    "elapsed": 0.0002326371,
                    "pagefaults": 0,
                    "cpucycles": 0,
                    "contextswitches": 0,
                    "instructions": 0,
                    "branchinstructions": 0,
                    "branchmisses": 0
                },
                {
                    "iterations": 10,
                    "elapsed": 0.0002010116,
                    "pagefaults": 0,
                    "cpucycles": 0,
                    "contextswitches": 0,
                    "instructions": 0,
                    "branchinstructions": 0,
                    "branchmisses": 0
                },
                {
                    "iterations": 10,
                    "elapsed": 0.000116269,
                    "pagefaults": 0,
                    "cpucycles": 0,
                    "contextswitches": 0,
                    "instructions": 0,
                    "branchinstructions": 0,
                    "branchmisses": 0
                },
                {
                    "iterations": 10,
                    "elapsed": 0.0001158723,
                    "pagefaults": 0,
                    "cpucycles": 0,
                    "contextswitches": 0,
                    "instructions": 0,
                    "branchinstructions": 0,
                    "branchmisses": 0
                },
                {
                    "iterations": 10,
                    "elapsed": 0.0001163081,
                    "pagefaults": 0,
                    "cpucycles": 0,
                    "contextswitches": 0,
                    "instructions": 0,
                    "branchinstructions": 0,
                    "branchmisses": 0
                },
                {
                    "iterations": 10,
                    "elapsed": 0.0001172448,
                    "pagefaults": 0,
                    "cpucycles": 0,
                    "contextswitches": 0,
                    "instructions": 0,
                    "branchinstructions": 0,
                    "branchmisses": 0
                },
                {
                    "iterations": 10,
                    "elapsed": 0.0001159464,
                    "pagefaults": 0,
                    "cpucycles": 0,
                    "contextswitches": 0,
                    "instructions": 0,
                    "branchinstructions": 0,
                    "branchmisses": 0
                },
                {
                    "iterations": 10,
                    "elapsed": 0.0001162109,
                    "pagefaults": 0,
                    "cpucycles": 0,
                    "contextswitches": 0,
                    "instructions": 0,
                    "branchinstructions": 0,
                    "branchmisses": 0
                },
                {
                    "iterations": 10,
                    "elapsed": 0.0001160626,
                    "pagefaults": 0,
                    "cpucycles": 0,
                    "contextswitches": 0,
                    "instructions": 0,
                    "branchinstructions": 0,
                    "branchmisses": 0
                }
            ]
        },
        {
            "title": "Scheduler Performance Comparison",
            "name": "NestedParallel_V2",
            "unit": "operation",
            "batch": 1,
            "complexityN": -1,
            "epochs": 11,
            "clockResolution": 2e-08,
            "clockResolutionMultiple": 1000,
            "maxEpochTime": 0.1,
            "minEpochTime": 0.001,
            "minEpochIterations": 5,
            "epochIterations": 10,
            "warmup": 3,
            "relative": 1,
            "median(elapsed)": 0.0001341735,
            "medianAbsolutePercentError(elapsed)": 0.0428605516438402,
            "median(instructions)": 0,
            "medianAbsolutePercentError(instructions)": 0,
            "median(cpucycles)": 0,
            "median(contextswitches)": 0,
            "median(pagefaults)": 0,
            "median(branchinstructions)": 0,
            "median(branchmisses)": 0,
            "totalTime": 0.01410216,
            "measurements": [
                {
                    "iterations": 8,
                    "elapsed": 0.000139911125,
                    "pagefaults": 0,
                    "cpucycles": 0,
                    "contextswitches": 0,
                    "instructions": 0,
                    "branchinstructions": 0,
                    "branchmisses": 0
                },
                {
                    "iterations": 7,
                    "elapsed": 0.000154859,
                    "pagefaults": 0,
                    "cpucycles": 0,
                    "contextswitches": 0,
                    "instructions": 0,
                    "branchinstructions": 0,
                    "branchmisses": 0
                },
                {
                    "iterations": 10,
                    "elapsed": 0.0001278456,
                    "pagefaults": 0,
                    "cpucycles": 0,
                    "contextswitches": 0,
                    "instructions": 0,
                    "branchinstructions": 0,
                    "branchmisses": 0
                },
                {
                    "iterations": 10,
                    "elapsed": 0.0001469873,
                    "pagefaults": 0,
                    "cpucycles": 0,
                    "contextswitches": 0,
                    "instructions": 0,
                    "branchinstructions": 0,
                    "branchmisses": 0
                },
                {
                    "iterations": 10,
                    "elapsed": 0.0001310095,
                    "pagefaults": 0,
                    "cpucycles": 0,
                    "contextswitches": 0,
                    "instructions": 0,
                    "branchinstructions": 0,
                    "branchmisses": 0
                },
                {
                    "iterations": 10,
                    "elapsed": 0.0001363675,
                    "pagefaults": 0,
                    "cpucycles": 0,
                    "contextswitches": 0,
                    "instructions": 0,
                    "branchinstructions": 0,
                    "branchmisses": 0
                },
                {
                    "iterations": 10,
                    "elapsed": 0.0001364216,
                    "pagefaults": 0,
                    "cpucycles": 0,
                    "contextswitches": 0,
                    "instructions": 0,
                    "branchinstructions": 0,
                    "branchmisses": 0
                },
                {
                    "iterations": 10,
                    "elapsed": 0.0001262647,
                    "pagefaults": 0,
                    "cpucycles": 0,
                    "contextswitches": 0,
                    "instructions": 0,
                    "branchinstructions": 0,
                    "branchmisses": 0
                },
                {
                    "iterations": 10,
                    "elapsed": 0.000122157,
                    "pagefaults": 0,
                    "cpucycles": 0,
                    "contextswitches": 0,
                    "instructions": 0,
                    "branchinstructions": 0,
                    "branchmisses": 0
                },
                {
                    "iterations": 10,
                    "elapsed": 0.0001341735,
                    "pagefaults": 0,
                    "cpucycles": 0,
                    "contextswitches": 0,
                    "instructions": 0,
                    "branchinstructions": 0,
                    "branchmisses": 0
                },
                {
                    "iterations": 10,
                    "elapsed": 0.0001286591,
                    "pagefaults": 0,
                    "cpucycles": 0,
                    "contextswitches": 0,
                    "instructions": 0,
                    "branchinstructions": 0,
                    "branchmisses": 0
                }
            ]
        }
    ]
}